drama_agent/__init__.py
drama_agent/drama_agent.py
drama_agent/importance_weighted_retriever.py
drama_agent/memory.py
drama_agent/myfaiss.py
drama_agent/profile.py
drama_agent/run_agent.py
drama_agent/pyarmor_runtime_000000/__init__.py
drama_agent/pyarmor_runtime_000000/pyarmor_runtime.so
drama_agent/template/0.0 seg_template.txt
drama_agent/template/_get_insights_on_event.txt
drama_agent/template/_get_insights_on_topic.txt
drama_agent/template/_get_topics_of_reflection.txt
drama_agent/template/answer_stylize_template.txt
drama_agent/template/answer_template.txt
drama_agent/template/question_stylize_template.txt
drama_agent/template/seg_template.txt
drama_agent/template/summarize.txt
drama_agent/template/summary_template.txt
drama_agent/template/summary_template_CoN.txt
drama_agent/template/summary_template_CoT.txt
drama_agent/template/summary_template_preview.txt
drama_agent/template_en/0.0 seg_template.txt
drama_agent/template_en/_get_insights_on_event.txt
drama_agent/template_en/_get_insights_on_topic.txt
drama_agent/template_en/_get_topics_of_reflection.txt
drama_agent/template_en/answer_template.txt
drama_agent/template_en/seg_template.txt
drama_agent/template_en/summarize.txt
drama_agent/template_en/summary_template.txt
drama_agent/template_en/summary_template_preview.txt
drama_agent/utils/__init__.py
drama_agent/utils/bm25-wrong.py
drama_agent/utils/bm25.py
drama_agent/utils/chUtil.py
drama_agent/utils/dbjson2json.py
drama_agent/utils/format_check.py
drama_agent/utils/openaitest.py
drama_agent/utils/simulation.py
drama_agent/utils/text_similarity.py
drama_agent/utils/utils.py
drama_agent-0.1.4.dist-info/METADATA
drama_agent-0.1.4.dist-info/WHEEL
drama_agent-0.1.4.dist-info/top_level.txt
drama_agent-0.1.4.dist-info/RECORD
